<?xml version="1.0" encoding="UTF-8" ?>
<?xml-stylesheet type="text/xsl" href="searching.xsl" ?>
<student>
    <sd>
        <name>Akhila</name>
        <roll>61</roll>
        <age>34</age>
        <marks>234</marks>
        <grade>A</grade>
    </sd>
    <sd>
        <name>Anantha</name>
        <roll>62</roll>
        <age>22</age>
        <marks>67</marks>
        <grade>C</grade>
    </sd>
    <sd>
        <name>Vivek</name>
        <roll>119</roll>
        <age>28</age>
        <marks>23</marks>
        <grade>B</grade>
    </sd>
    <sd>
        <name>Adil</name>
        <roll>56</roll>
        <age>29</age>
        <marks>100</marks>
        <grade>C</grade>
    </sd>
    <sd>
        <name>Gopal</name>
        <roll>78</roll>
        <age>33</age>
        <marks>23</marks>
        <grade>A</grade>
    </sd>
</student>